<?xml version="1.0" encoding="iso-8859-1"?>
<wiki_cat_infos>
  <wiki_articles_fields>
    <wiki_id>136</wiki_id>
    <wiki_id_contents>649</wiki_id_contents>
    <wiki_title>Personnalisation</wiki_title>
    <wiki_encoded_title>personnalisation</wiki_encoded_title>
    <wiki_hits>621</wiki_hits>
    <wiki_id_cat>40</wiki_id_cat>
    <wiki_is_cat>1</wiki_is_cat>
    <wiki_defined_status>0</wiki_defined_status>
    <wiki_undefined_status></wiki_undefined_status>
    <wiki_redirect>0</wiki_redirect>
    <wiki_auth></wiki_auth>
  </wiki_articles_fields>
  <wiki_cats_fields>
    <wiki_cat_id>40</wiki_cat_id>
    <wiki_cat_id_parent>13</wiki_cat_id_parent>
    <wiki_cat_article_id>136</wiki_cat_article_id>
  </wiki_cats_fields>
  <wiki_contents_fields>
    <wiki_con_id_contents>649</wiki_con_id_contents>
    <wiki_con_id_article>136</wiki_con_id_article>
    <wiki_menu></wiki_menu>
    <wiki_content>[table style="float:right;"]
   [row]
      [head colspan="2"]Personnalisation[/head]
   [/row]
   [row]
      [col]Auteur[/col]
      [col][url=/user/profile/1393]ReidLos[/url][/col]
   [/row]
   [row]
      [col]Version actuelle[/col]
      [col]4.0[/col]
   [/row]
   [row]
      [col]Date de sortie[/col]
      [col]juillet 2012[/col]
   [/row]
   [row]
      [col]Compatibilité[/col]
      [col]PHPBoost 4.0[/col]
   [/row]
   [row]
      [col]Démonstration[/col]
      [col][url=http://demo.phpboost.com/customization/?url=/interface]Personnalisation[/url][/col]
   [/row]
[/table]

[align=center]
   [size=20][b]Module Personnalisation[/b][/size]
   [img]images/utilisation/modules/customization/logo.png[/img]
[/align]







[b]Description :[/b] Ce module vous permet de personnaliser l'apparence de votre site.
Vous pouvez modifier le favicon ainsi que le logo de chaque thème dans une interface simplifiée.
Vous avez également la possibilité d'éditer les fichiers CSS de vos thèmes.</wiki_content>
    <wiki_activ>1</wiki_activ>
    <wiki_user_id>1393</wiki_user_id>
    <wiki_user_ip>90.6.60.78</wiki_user_ip>
    <wiki_timestamp>1355737634</wiki_timestamp>
  </wiki_contents_fields>
</wiki_cat>